orangewidget/__init__.py
orangewidget/gui.py
orangewidget/i18n_config.py
orangewidget/io.py
orangewidget/settings.py
orangewidget/version.py
orangewidget/widget.py
orangewidget/icons/Dlg_arrow.png
orangewidget/icons/Dlg_clear.png
orangewidget/icons/Dlg_down3.png
orangewidget/icons/Dlg_enter.png
orangewidget/icons/Dlg_pan_hand.png
orangewidget/icons/Dlg_redo.png
orangewidget/icons/Dlg_send.png
orangewidget/icons/Dlg_sort.png
orangewidget/icons/Dlg_undo.png
orangewidget/icons/Dlg_up3.png
orangewidget/icons/Dlg_zoom.png
orangewidget/icons/Dlg_zoom_reset.png
orangewidget/icons/Dlg_zoom_selection.png
orangewidget/icons/Unknown.png
orangewidget/icons/chart-hover.svg
orangewidget/icons/chart.svg
orangewidget/icons/downgreenarrow.png
orangewidget/icons/error.png
orangewidget/icons/help-hover.svg
orangewidget/icons/help.svg
orangewidget/icons/information.png
orangewidget/icons/input-empty.svg
orangewidget/icons/input-partial.svg
orangewidget/icons/input.svg
orangewidget/icons/output-empty.svg
orangewidget/icons/output-partial.svg
orangewidget/icons/output.svg
orangewidget/icons/report-hover.svg
orangewidget/icons/report.svg
orangewidget/icons/reset-hover.svg
orangewidget/icons/reset.svg
orangewidget/icons/upgreenarrow.png
orangewidget/icons/visual-settings-hover.svg
orangewidget/icons/visual-settings.svg
orangewidget/icons/warning.png
orangewidget/locale/widget.en.yml
orangewidget/locale/widget.zh.yml
orangewidget/report/__init__.py
orangewidget/report/index.html
orangewidget/report/owreport.py
orangewidget/report/report.py
orangewidget/report/icons/delete.svg
orangewidget/report/icons/scheme.svg
orangewidget/report/tests/__init__.py
orangewidget/report/tests/test_report.py
orangewidget/tests/__init__.py
orangewidget/tests/base.py
orangewidget/tests/test_context_handler.py
orangewidget/tests/test_control_getter.py
orangewidget/tests/test_gui.py
orangewidget/tests/test_io.py
orangewidget/tests/test_matplotlib_export.py
orangewidget/tests/test_setting_provider.py
bluewhale_widget_base-4.16.0.dist-info/LICENSE
bluewhale_widget_base-4.16.0.dist-info/METADATA
bluewhale_widget_base-4.16.0.dist-info/WHEEL
bluewhale_widget_base-4.16.0.dist-info/top_level.txt
bluewhale_widget_base-4.16.0.dist-info/RECORD
