Metadata-Version: 2.1
Name: bluewhale-widget-base
Version: 4.16.0
Summary: Base Widget for Orange Canvas
Home-page: http://orange.biolab.si/
Author: 大圣实验楼
Author-email: dashenglab@163.com
License: GPLv3+
Keywords: workflow,widget
Platform: UNKNOWN
Classifier: Development Status :: 4 - Beta
Classifier: Environment :: X11 Applications :: Qt
Classifier: Environment :: Console
Classifier: Environment :: Plugins
Classifier: Programming Language :: Python
Classifier: License :: OSI Approved :: GNU General Public License v3 or later (GPLv3+)
Classifier: Operating System :: POSIX
Classifier: Operating System :: Microsoft :: Windows
Classifier: Topic :: Scientific/Engineering :: Artificial Intelligence
Classifier: Topic :: Scientific/Engineering :: Visualization
Classifier: Topic :: Software Development :: Libraries :: Python Modules
Classifier: Intended Audience :: Education
Classifier: Intended Audience :: Science/Research
Classifier: Intended Audience :: Developers
Requires-Python: >=3.6
Requires-Dist: matplotlib
Requires-Dist: pyqtgraph
Requires-Dist: AnyQt
Requires-Dist: typing-extensions (>=3.7.4.3)
Requires-Dist: bluewhale-canvas-core (<0.2a,>=0.1.19)
Requires-Dist: appnope ; sys_platform == "darwin"
